fall_detection/__init__.py
fall_detection/api.py
fall_detection/detector.py
fall_detection/models/best.pt
fall_detection/models/best_fp16.onnx
human_fall_detection-0.1.2.dist-info/licenses/LICENCE
human_fall_detection-0.1.2.dist-info/METADATA
human_fall_detection-0.1.2.dist-info/WHEEL
human_fall_detection-0.1.2.dist-info/top_level.txt
human_fall_detection-0.1.2.dist-info/RECORD
