Metadata-Version: 2.4
Name: human-fall-detection
Version: 0.1.2
Summary: Static fall detection based on YOLOv8n
Project-URL: Homepage, https://github.com/TomokotoKiyoshi/Human-Fall-Detection.git
Requires-Python: >=3.11
License-File: LICENCE
Requires-Dist: ipython>=9.5.0
Requires-Dist: onnx>=1.19.0
Requires-Dist: pip>=25.2
Requires-Dist: scikit-learn>=1.7.2
Requires-Dist: seaborn>=0.13.2
Requires-Dist: tqdm>=4.67.1
Requires-Dist: ultralytics>=8.3.202
Dynamic: license-file
